colabxterm/VERSION
colabxterm/__init__.py
colabxterm/__main__.py
colabxterm/manager.py
colabxterm/notebook.py
colabxterm/xterm.py
colabxterm/client/dist/index.html
colabxterm/client/dist/main.js
colabxterm/client/dist/main.js.LICENSE.txt
colab_xterm-0.2.0.dist-info/LICENSE
colab_xterm-0.2.0.dist-info/METADATA
colab_xterm-0.2.0.dist-info/WHEEL
colab_xterm-0.2.0.dist-info/top_level.txt
colab_xterm-0.2.0.dist-info/RECORD
