Metadata-Version: 2.1
Name: colab-xterm
Version: 0.2.0
Summary: Open a terminal in colab, including the free tier.
Home-page: https://github.com/InfuseAI/colab-xterm
Project-URL: Bug Tracker, https://github.com/InfuseAI/colab-xterm/issues
Requires-Python: >=3.6
License-File: LICENSE
Requires-Dist: ptyprocess (~=0.7.0)
Requires-Dist: tornado (>5.1)
Provides-Extra: dev
Requires-Dist: jupyter ; extra == 'dev'
Requires-Dist: twine ; extra == 'dev'
